README.md
setup.py
tax_cake/__init__.py
tax_cake/bonus_tax.py
tax_cake/tax_rules.py
tax_cake/test.py
tax_cake/year_salary_tax.py
tax_cake.egg-info/PKG-INFO
tax_cake.egg-info/SOURCES.txt
tax_cake.egg-info/dependency_links.txt
tax_cake.egg-info/entry_points.txt
tax_cake.egg-info/top_level.txt