Metadata-Version: 1.0
Name: tax-cake
Version: 0.0.3
Summary: 个税和年终奖计算工具
Home-page: https://github.com/taojigu
Author: gujitao
Author-email: taojigu@163.com
License: UNKNOWN
Platform: UNKNOWN
